LICENSE
README.md
setup.cfg
setup.py
logni/__init__.py
logni/cfgni.py
logni/consolestream.py
logni/filestream.py
logni/logni.py
logni/utilni.py
logni.egg-info/PKG-INFO
logni.egg-info/SOURCES.txt
logni.egg-info/dependency_links.txt
logni.egg-info/top_level.txt