Metadata-Version: 2.1
Name: logni
Version: 0.2.3
Summary: python library for event logging and application states
Home-page: https://github.com/erikni/logni.py
Download-URL: https://github.com/erik/logni.py/archive/master.zip
Author: Erik Brozek
Author-email: erik@brozek.name
License: MIT
Keywords: logging,logging-library,logger
Classifier: Development Status :: 4 - Beta
Classifier: Programming Language :: Python :: 3
Classifier: Programming Language :: Python :: 3.7
Classifier: Programming Language :: Python :: 3.8
Classifier: Programming Language :: Python :: 3.9
Classifier: Programming Language :: Python :: 3.10
Classifier: Programming Language :: Python :: 3.11
Classifier: License :: OSI Approved :: MIT License
Classifier: Topic :: System :: Logging
Requires-Python: >=3.7
License-File: LICENSE
